diff_nurbs/__init__.py
diff_nurbs/nurbs.py
diff_nurbs-0.0.3.dist-info/LICENSE
diff_nurbs-0.0.3.dist-info/METADATA
diff_nurbs-0.0.3.dist-info/WHEEL
diff_nurbs-0.0.3.dist-info/top_level.txt
diff_nurbs-0.0.3.dist-info/RECORD
